LICENSE.txt
MANIFEST.in
README.rst
config.example.ini
pathfix.py
setup.py
pathfix.py.egg-info/PKG-INFO
pathfix.py.egg-info/SOURCES.txt
pathfix.py.egg-info/dependency_links.txt
pathfix.py.egg-info/top_level.txt